[{"Pincode":"481445","Name":"Agasi B.O","Block":"Katangi","District":"Balaghat","State":"Madhya Pradesh"},{"Pincode":"481332","Name":"Agri B.O","Block":"Katangi","District":"Balaghat","State":"Madhya Pradesh"},{"Pincode":"481117","Name":"Alna B.O","Block":"Baihar","District":"Balaghat","State":"Madhya Pradesh"},{"Pincode":"481335","Name":"Amai B.O","Block":"Waraseoni","District":"Balaghat","State":"Madhya Pradesh"},{"Pincode":"481222","Name":"Ameda B.O","Block":"Lanji","District":"Balaghat","State":"Madhya Pradesh"},{"Pincode":"481102","Name":"Ameda B.O","Block":"Balaghat","District":"Balaghat","State":"Madhya Pradesh"},{"Pincode":"481111","Name":"Amgaon B.O","Block":"Baihar","District":"Balaghat","State":"Madhya Pradesh"},{"Pincode":"481335","Name":"Arambha B.O","Block":"Waraseoni","District":"Balaghat","State":"Madhya Pradesh"},{"Pincode":"481337","Name":"Atri B.O","Block":"Khairlanji","District":"Balaghat","State":"Madhya Pradesh"},{"Pincode":"481331","Name":"Badgaon B.O","Block":"Lalburra","District":"Balaghat","State":"Madhya Pradesh"},{"Pincode":"481222","Name":"Badgaon B.O","Block":"Lanji","District":"Balaghat","State":"Madhya Pradesh"},{"Pincode":"481665","Name":"Badhar B.O","Block":"Balaghat","District":"Balaghat","State":"Madhya Pradesh"},{"Pincode":"481556","Name":"Bagholi B.O","Block":"Baihar","District":"Balaghat","State":"Madhya Pradesh"},{"Pincode":"481441","Name":"Bagholi B.O","Block":"Lalbarra","District":"Balaghat","State":"Madhya Pradesh"},{"Pincode":"481224","Name":"Bahela B.O","Block":"Lanji","District":"Balaghat","State":"Madhya Pradesh"},{"Pincode":"481111","Name":"Baihar S.O","Block":"Baihar","District":"Balaghat","State":"Madhya Pradesh"},{"Pincode":"481051","Name":"Bakal B.O","Block":"Baihar","District":"Balaghat","State":"Madhya Pradesh"},{"Pincode":"481335","Name":"Bakera B.O","Block":"Waraseoni","District":"Balaghat","State":"Madhya Pradesh"},{"Pincode":"481441","Name":"Bakoda B.O","Block":"Lalburra","District":"Balaghat","State":"Madhya Pradesh"},{"Pincode":"481001","Name":"Balaghat City S.O","Block":"Balaghat","District":"Balaghat","State":"Madhya Pradesh"},{"Pincode":"481001","Name":"Balaghat H.O","Block":"Balaghat","District":"Balaghat","State":"Madhya Pradesh"},{"Pincode":"481001","Name":"Balaghat R.S. S.O","Block":"Balaghat","District":"Balaghat","State":"Madhya Pradesh"},{"Pincode":"481449","Name":"Bamhani B.O","Block":"Tirodi","District":"Balaghat","State":"Madhya Pradesh"},{"Pincode":"481445","Name":"Banera B.O","Block":"Katangi","District":"Balaghat","State":"Madhya Pradesh"},{"Pincode":"481226","Name":"Beni B.O","Block":"Khairlanji","District":"Balaghat","State":"Madhya Pradesh"},{"Pincode":"481337","Name":"Bhandarbodi B.O","Block":"Khairlanji","District":"Balaghat","State":"Madhya Pradesh"},{"Pincode":"481105","Name":"Bhanderi B.O","Block":"Baihar","District":"Balaghat","State":"Madhya Pradesh"},{"Pincode":"481115","Name":"Bhanegaon B.O","Block":"Kirnapur","District":"Balaghat","State":"Madhya Pradesh"},{"Pincode":"481102","Name":"Bharveli S.O","Block":"Balaghat","District":"Balaghat","State":"Madhya Pradesh"},{"Pincode":"481337","Name":"Bhaurgarh B.O","Block":"Khairlanji","District":"Balaghat","State":"Madhya Pradesh"},{"Pincode":"481335","Name":"Bhendara B.O","Block":"Waraseoni","District":"Balaghat","State":"Madhya Pradesh"},{"Pincode":"481556","Name":"Bhidi B.O","Block":"Baihar","District":"Balaghat","State":"Madhya Pradesh"},{"Pincode":"481556","Name":"Bhikewada B.O","Block":"Baihar","District":"Balaghat","State":"Madhya Pradesh"},{"Pincode":"481051","Name":"Bijatola B.O","Block":"Baihar","District":"Balaghat","State":"Madhya Pradesh"},{"Pincode":"481051","Name":"Birsa S.O","Block":"Baihar","District":"Balaghat","State":"Madhya Pradesh"},{"Pincode":"481331","Name":"Birsola B.O","Block":"Lalburra","District":"Balaghat","State":"Madhya Pradesh"},{"Pincode":"481111","Name":"Birwa B.O","Block":"Baihar","District":"Balaghat","State":"Madhya Pradesh"},{"Pincode":"481222","Name":"Bisoni B.O","Block":"Lanji","District":"Balaghat","State":"Madhya Pradesh"},{"Pincode":"481111","Name":"Boda B.O","Block":"Baihar","District":"Balaghat","State":"Madhya Pradesh"},{"Pincode":"481102","Name":"Boda B.O","Block":"Balaghat","District":"Balaghat","State":"Madhya Pradesh"},{"Pincode":"481222","Name":"Bolegaon B.O","Block":"Lanji","District":"Balaghat","State":"Madhya Pradesh"},{"Pincode":"481115","Name":"Borgaon B.O","Block":"Kirnapur","District":"Balaghat","State":"Madhya Pradesh"},{"Pincode":"481441","Name":"Bori B.O","Block":"Lalbarra","District":"Balaghat","State":"Madhya Pradesh"},{"Pincode":"481332","Name":"Budbuda S.O","Block":"Waraseoni","District":"Balaghat","State":"Madhya Pradesh"},{"Pincode":"481226","Name":"Budhi B.O","Block":"Kirnapur","District":"Balaghat","State":"Madhya Pradesh"},{"Pincode":"481102","Name":"Chalisbodi B.O","Block":"Balaghat","District":"Balaghat","State":"Madhya Pradesh"},{"Pincode":"481556","Name":"Chandana B.O","Block":"Baihar","District":"Balaghat","State":"Madhya Pradesh"},{"Pincode":"481551","Name":"Charega R.S. B.O","Block":"Balaghat","District":"Balaghat","State":"Madhya Pradesh"},{"Pincode":"481226","Name":"Chikhla B.O","Block":"Kirnapur","District":"Balaghat","State":"Madhya Pradesh"},{"Pincode":"481335","Name":"Chikhla Bandh B.O","Block":"Waraseoni","District":"Balaghat","State":"Madhya Pradesh"},{"Pincode":"481331","Name":"Chillod B.O","Block":"Waraseoni","District":"Balaghat","State":"Madhya Pradesh"},{"Pincode":"481441","Name":"Dadiya B.O","Block":"Lalbarra","District":"Balaghat","State":"Madhya Pradesh"},{"Pincode":"481115","Name":"Dahedi B.O","Block":"Kirnapur","District":"Balaghat","State":"Madhya Pradesh"},{"Pincode":"481051","Name":"Damoh B.O","Block":"Baihar","District":"Balaghat","State":"Madhya Pradesh"},{"Pincode":"481331","Name":"Deeni B.O","Block":"Waraseoni","District":"Balaghat","State":"Madhya Pradesh"},{"Pincode":"481001","Name":"Deori B.O","Block":"Balaghat","District":"Balaghat","State":"Madhya Pradesh"},{"Pincode":"481449","Name":"Deori B.O","Block":"Katangi","District":"Balaghat","State":"Madhya Pradesh"},{"Pincode":"481224","Name":"Devalgaon B.O","Block":"Lanji","District":"Balaghat","State":"Madhya Pradesh"},{"Pincode":"481102","Name":"Dhansua B.O","Block":"Balaghat","District":"Balaghat","State":"Madhya Pradesh"},{"Pincode":"481449","Name":"Digdha B.O","Block":"Katangi","District":"Balaghat","State":"Madhya Pradesh"},{"Pincode":"481556","Name":"Dongiriya B.O","Block":"Baihar","District":"Balaghat","State":"Madhya Pradesh"},{"Pincode":"481105","Name":"Dora B.O","Block":"Baihar","District":"Balaghat","State":"Madhya Pradesh"},{"Pincode":"481337","Name":"Fulchur B.O","Block":"Khairlanji","District":"Balaghat","State":"Madhya Pradesh"},{"Pincode":"481117","Name":"Garhi S.O (Balaghat)","Block":"Baihar","District":"Balaghat","State":"Madhya Pradesh"},{"Pincode":"481001","Name":"Garra B.O","Block":"Balaghat","District":"Balaghat","State":"Madhya Pradesh"},{"Pincode":"481331","Name":"Garra B.O","Block":"Waraseoni","District":"Balaghat","State":"Madhya Pradesh"},{"Pincode":"481051","Name":"Garra Tola B.O","Block":"Baihar","District":"Balaghat","State":"Madhya Pradesh"},{"Pincode":"481224","Name":"Ghansa B.O","Block":"Lanji","District":"Balaghat","State":"Madhya Pradesh"},{"Pincode":"481441","Name":"Ghoti B.O","Block":"Lalbarra","District":"Balaghat","State":"Madhya Pradesh"},{"Pincode":"481335","Name":"Ghoti B.O","Block":"Waraseoni","District":"Balaghat","State":"Madhya Pradesh"},{"Pincode":"481551","Name":"Ghunadi B.O","Block":"Balaghat","District":"Balaghat","State":"Madhya Pradesh"},{"Pincode":"481001","Name":"Gongalai B.O","Block":"Balaghat","District":"Balaghat","State":"Madhya Pradesh"},{"Pincode":"481449","Name":"Goreghat B.O","Block":"Katangi","District":"Balaghat","State":"Madhya Pradesh"},{"Pincode":"481105","Name":"Gudma B.O","Block":"Baihar","District":"Balaghat","State":"Madhya Pradesh"},{"Pincode":"481116","Name":"Gudma B.O","Block":"Baihar","District":"Balaghat","State":"Madhya Pradesh"},{"Pincode":"481551","Name":"Gudru R.S. B.O","Block":"Balaghat","District":"Balaghat","State":"Madhya Pradesh"},{"Pincode":"481449","Name":"Hardoli B.O","Block":"Katangi","District":"Balaghat","State":"Madhya Pradesh"},{"Pincode":"481226","Name":"Hatta Road B.O","Block":"Kirnapur","District":"Balaghat","State":"Madhya Pradesh"},{"Pincode":"481226","Name":"Hatta S.O (Balaghat)","Block":"Kirnapur","District":"Balaghat","State":"Madhya Pradesh"},{"Pincode":"481115","Name":"Hirri B.O","Block":"Kirnapur","District":"Balaghat","State":"Madhya Pradesh"},{"Pincode":"481117","Name":"Jaitpuri B.O","Block":"Baihar","District":"Balaghat","State":"Madhya Pradesh"},{"Pincode":"481441","Name":"Jam B.O","Block":"Lalburra","District":"Balaghat","State":"Madhya Pradesh"},{"Pincode":"481445","Name":"Jam B.O","Block":"Katangi","District":"Balaghat","State":"Madhya Pradesh"},{"Pincode":"481116","Name":"Janpur B.O","Block":"Baihar","District":"Balaghat","State":"Madhya Pradesh"},{"Pincode":"481332","Name":"Jarah Mohgaon B.O","Block":"Katangi","District":"Balaghat","State":"Madhya Pradesh"},{"Pincode":"481105","Name":"Jatta B.O","Block":"Baihar","District":"Balaghat","State":"Madhya Pradesh"},{"Pincode":"481331","Name":"Jhaliwada B.O","Block":"Waraseoni","District":"Balaghat","State":"Madhya Pradesh"},{"Pincode":"481337","Name":"Kachekhani B.O","Block":"Khairlanji","District":"Balaghat","State":"Madhya Pradesh"},{"Pincode":"481051","Name":"Kachnari B.O","Block":"Baihar","District":"Balaghat","State":"Madhya Pradesh"},{"Pincode":"481111","Name":"Kalegaon B.O","Block":"Baihar","District":"Balaghat","State":"Madhya Pradesh"},{"Pincode":"481222","Name":"Kalimati B.O","Block":"Lanji","District":"Balaghat","State":"Madhya Pradesh"},{"Pincode":"481115","Name":"Kandrikala B.O","Block":"Kirnapur","District":"Balaghat","State":"Madhya Pradesh"},{"Pincode":"481441","Name":"Kanjai B.O","Block":"Lalbarra","District":"Balaghat","State":"Madhya Pradesh"},{"Pincode":"481001","Name":"Kanki B.O","Block":"Laburra","District":"Balaghat","State":"Madhya Pradesh"},{"Pincode":"481116","Name":"Karamsara B.O","Block":"Baihar","District":"Balaghat","State":"Madhya Pradesh"},{"Pincode":"481224","Name":"Karanja S.O (Balaghat)","Block":"Lanji","District":"Balaghat","State":"Madhya Pradesh"},{"Pincode":"481111","Name":"Kareli B.O","Block":"Baihar","District":"Balaghat","State":"Madhya Pradesh"},{"Pincode":"481116","Name":"Karhu B.O","Block":"Baihar","District":"Balaghat","State":"Madhya Pradesh"},{"Pincode":"481226","Name":"Kariadand B.O","Block":"Kirnapur","District":"Balaghat","State":"Madhya Pradesh"},{"Pincode":"481331","Name":"Kaspur B.O","Block":"Waraseoni","District":"Balaghat","State":"Madhya Pradesh"},{"Pincode":"481445","Name":"Katangi S.O (Balaghat)","Block":"Katangi","District":"Balaghat","State":"Madhya Pradesh"},{"Pincode":"481332","Name":"Katanjhari B.O","Block":"Lalbarra","District":"Balaghat","State":"Madhya Pradesh"},{"Pincode":"481445","Name":"Katedara B.O","Block":"Katangi","District":"Balaghat","State":"Madhya Pradesh"},{"Pincode":"481445","Name":"Katera B.O","Block":"Katangi","District":"Balaghat","State":"Madhya Pradesh"},{"Pincode":"481337","Name":"Katori B.O","Block":"Khairlanji","District":"Balaghat","State":"Madhya Pradesh"},{"Pincode":"481331","Name":"Kaydi B.O","Block":"Waraseoni","District":"Balaghat","State":"Madhya Pradesh"},{"Pincode":"481226","Name":"Keshalewada B.O","Block":"Kirnapur","District":"Balaghat","State":"Madhya Pradesh"},{"Pincode":"481335","Name":"Khadkhadi B.O","Block":"Waraseoni","District":"Balaghat","State":"Madhya Pradesh"},{"Pincode":"481337","Name":"Khairi B.O","Block":"Khairlanji","District":"Balaghat","State":"Madhya Pradesh"},{"Pincode":"481337","Name":"Khairlanji S.O","Block":"Waraseoni","District":"Balaghat","State":"Madhya Pradesh"},{"Pincode":"481445","Name":"Khamaria B.O","Block":"Katangi","District":"Balaghat","State":"Madhya Pradesh"},{"Pincode":"481331","Name":"Khamariya Bazar B.O","Block":"Lalbarra","District":"Balaghat","State":"Madhya Pradesh"},{"Pincode":"481226","Name":"Khara B.O","Block":"Kirnapur","District":"Balaghat","State":"Madhya Pradesh"},{"Pincode":"481441","Name":"Khari B.O","Block":"Lalburra","District":"Balaghat","State":"Madhya Pradesh"},{"Pincode":"481556","Name":"Kharpadia B.O","Block":"Baihar","District":"Balaghat","State":"Madhya Pradesh"},{"Pincode":"481111","Name":"Khurmundi B.O","Block":"Baihar","District":"Balaghat","State":"Madhya Pradesh"},{"Pincode":"481115","Name":"Kinhi B.O","Block":"Kirnapur","District":"Balaghat","State":"Madhya Pradesh"},{"Pincode":"481051","Name":"Kinia B.O","Block":"Baihar","District":"Balaghat","State":"Madhya Pradesh"},{"Pincode":"481105","Name":"Kiniya Kandai B.O","Block":"Baihar","District":"Balaghat","State":"Madhya Pradesh"},{"Pincode":"481115","Name":"Kirnapur S.O","Block":"Kirnapur","District":"Balaghat","State":"Madhya Pradesh"},{"Pincode":"481551","Name":"Kochewada B.O","Block":"Balaghat","District":"Balaghat","State":"Madhya Pradesh"},{"Pincode":"481332","Name":"Kochewahi B.O","Block":"Waraseoni","District":"Balaghat","State":"Madhya Pradesh"},{"Pincode":"481331","Name":"Koste B.O","Block":"Waraseoni","District":"Balaghat","State":"Madhya Pradesh"},{"Pincode":"481335","Name":"Kothurna B.O","Block":"Waraseoni","District":"Balaghat","State":"Madhya Pradesh"},{"Pincode":"481449","Name":"Koylari B.O","Block":"Katangi","District":"Balaghat","State":"Madhya Pradesh"},{"Pincode":"481117","Name":"Kukarra B.O","Block":"Baihar","District":"Balaghat","State":"Madhya Pradesh"},{"Pincode":"481224","Name":"Kulpa B.O","Block":"Lanji","District":"Balaghat","State":"Madhya Pradesh"},{"Pincode":"481337","Name":"Kumhali B.O","Block":"Khairlanji","District":"Balaghat","State":"Madhya Pradesh"},{"Pincode":"481001","Name":"Kumhari B.O","Block":"Balaghat","District":"Balaghat","State":"Madhya Pradesh"},{"Pincode":"481224","Name":"Kumharikala B.O","Block":"Lanji","District":"Balaghat","State":"Madhya Pradesh"},{"Pincode":"481556","Name":"Kurenda B.O","Block":"Baihar","District":"Balaghat","State":"Madhya Pradesh"},{"Pincode":"481224","Name":"Ladsa B.O","Block":"Lanji","District":"Balaghat","State":"Madhya Pradesh"},{"Pincode":"481331","Name":"Ladsada B.O","Block":"Waraseoni","District":"Balaghat","State":"Madhya Pradesh"},{"Pincode":"481441","Name":"Lalbarra S.O","Block":"Lalbarra","District":"Balaghat","State":"Madhya Pradesh"},{"Pincode":"481335","Name":"Lalpur B.O","Block":"Waraseoni","District":"Balaghat","State":"Madhya Pradesh"},{"Pincode":"481551","Name":"Lamta S.O","Block":"Balaghat","District":"Balaghat","State":"Madhya Pradesh"},{"Pincode":"481222","Name":"Lanji S.O","Block":"Lanji","District":"Balaghat","State":"Madhya Pradesh"},{"Pincode":"481115","Name":"Laweri B.O","Block":"Kirnapur","District":"Balaghat","State":"Madhya Pradesh"},{"Pincode":"481335","Name":"Lawni B.O","Block":"Waraseoni","District":"Balaghat","State":"Madhya Pradesh"},{"Pincode":"481556","Name":"Linga B.O","Block":"Baihar","District":"Balaghat","State":"Madhya Pradesh"},{"Pincode":"481001","Name":"Linga B.O","Block":"Balaghat","District":"Balaghat","State":"Madhya Pradesh"},{"Pincode":"481449","Name":"Lingapounar B.O","Block":"Katangi","District":"Balaghat","State":"Madhya Pradesh"},{"Pincode":"481105","Name":"Lood B.O","Block":"Baihar","District":"Balaghat","State":"Madhya Pradesh"},{"Pincode":"481001","Name":"Magardarra B.O","Block":"Balaghat","District":"Balaghat","State":"Madhya Pradesh"},{"Pincode":"481449","Name":"Mahkepar B.O","Block":"Katangi","District":"Balaghat","State":"Madhya Pradesh"},{"Pincode":"481111","Name":"Majhgaon B.O","Block":"Baihar","District":"Balaghat","State":"Madhya Pradesh"},{"Pincode":"481116","Name":"Malanjkhand S.O","Block":"Baihar","District":"Balaghat","State":"Madhya Pradesh"},{"Pincode":"481051","Name":"Mandai B.O","Block":"Baihar","District":"Balaghat","State":"Madhya Pradesh"},{"Pincode":"481051","Name":"Manegaon B.O","Block":"Baihar","District":"Balaghat","State":"Madhya Pradesh"},{"Pincode":"481445","Name":"Manegaon B.O","Block":"Katangi","District":"Balaghat","State":"Madhya Pradesh"},{"Pincode":"481222","Name":"Maneri B.O","Block":"Lanji","District":"Balaghat","State":"Madhya Pradesh"},{"Pincode":"481331","Name":"Mangejhari B.O","Block":"Waraseoni","District":"Balaghat","State":"Madhya Pradesh"},{"Pincode":"481226","Name":"Mate B.O","Block":"Kirnapur","District":"Balaghat","State":"Madhya Pradesh"},{"Pincode":"481226","Name":"Mauda B.O","Block":"Kirnapur","District":"Balaghat","State":"Madhya Pradesh"},{"Pincode":"481331","Name":"Mehndiwada B.O","Block":"Waraseoni","District":"Balaghat","State":"Madhya Pradesh"},{"Pincode":"481331","Name":"Mendki B.O","Block":"Waraseoni","District":"Balaghat","State":"Madhya Pradesh"},{"Pincode":"481449","Name":"Miragpur B.O","Block":"Khairlanji","District":"Balaghat","State":"Madhya Pradesh"},{"Pincode":"481224","Name":"Miriya B.O","Block":"Lanji","District":"Balaghat","State":"Madhya Pradesh"},{"Pincode":"481116","Name":"Mohgaon (B) B.O","Block":"Baihar","District":"Balaghat","State":"Madhya Pradesh"},{"Pincode":"481551","Name":"Mohgaon Batua B.O","Block":"Balaghat","District":"Balaghat","State":"Madhya Pradesh"},{"Pincode":"481001","Name":"Mohgaon Dhapera B.O","Block":"Balaghat","District":"Balaghat","State":"Madhya Pradesh"},{"Pincode":"481226","Name":"Mohgaon-khurd B.O","Block":"Kirnapur","District":"Balaghat","State":"Madhya Pradesh"},{"Pincode":"481115","Name":"Mohjhari B.O","Block":"Kirnapur","District":"Balaghat","State":"Madhya Pradesh"},{"Pincode":"481551","Name":"Moriya B.O","Block":"Balaghat","District":"Balaghat","State":"Madhya Pradesh"},{"Pincode":"481337","Name":"Mowad B.O","Block":"Khairlanji","District":"Balaghat","State":"Madhya Pradesh"},{"Pincode":"481111","Name":"Mukki B.O","Block":"Baihar","District":"Balaghat","State":"Madhya Pradesh"},{"Pincode":"481551","Name":"Nagarwada R.S. B.O","Block":"Balaghat","District":"Balaghat","State":"Madhya Pradesh"},{"Pincode":"481441","Name":"Nagpura B.O","Block":"Lalbarra","District":"Balaghat","State":"Madhya Pradesh"},{"Pincode":"481115","Name":"Nakshi B.O","Block":"Kirnapur","District":"Balaghat","State":"Madhya Pradesh"},{"Pincode":"481449","Name":"Nandi B.O","Block":"Katangi","District":"Balaghat","State":"Madhya Pradesh"},{"Pincode":"481222","Name":"Nandora B.O","Block":"Lanji","District":"Balaghat","State":"Madhya Pradesh"},{"Pincode":"481335","Name":"Navegaon-3 B.O","Block":"Waraseoni","District":"Balaghat","State":"Madhya Pradesh"},{"Pincode":"481331","Name":"Neelji B.O","Block":"Lalbarra","District":"Balaghat","State":"Madhya Pradesh"},{"Pincode":"481331","Name":"Newargaon B.O","Block":"Waraseoni","District":"Balaghat","State":"Madhya Pradesh"},{"Pincode":"481441","Name":"Newargaon B.O","Block":"Lalbarra","District":"Balaghat","State":"Madhya Pradesh"},{"Pincode":"481226","Name":"Newargaon Kala B.O","Block":"Kirnapur","District":"Balaghat","State":"Madhya Pradesh"},{"Pincode":"481222","Name":"Newarwahi B.O","Block":"Lanji","District":"Balaghat","State":"Madhya Pradesh"},{"Pincode":"481116","Name":"Nikkum B.O","Block":"Baihar","District":"Balaghat","State":"Madhya Pradesh"},{"Pincode":"481551","Name":"Padriganj R.S B.O","Block":"Balaghat","District":"Balaghat","State":"Madhya Pradesh"},{"Pincode":"481115","Name":"Pala B.O","Block":"Kirnapur","District":"Balaghat","State":"Madhya Pradesh"},{"Pincode":"481117","Name":"Pandutala B.O","Block":"Baihar","District":"Balaghat","State":"Madhya Pradesh"},{"Pincode":"481556","Name":"Paraswada S.O","Block":"Baihar","District":"Balaghat","State":"Madhya Pradesh"},{"Pincode":"481449","Name":"Paraswaraghat B.O","Block":"Katangi","District":"Balaghat","State":"Madhya Pradesh"},{"Pincode":"481222","Name":"Pathargaon B.O","Block":"Lanji","District":"Balaghat","State":"Madhya Pradesh"},{"Pincode":"481661","Name":"Phoolsagar B.O","Block":"Balaghat","District":"Balaghat","State":"Madhya Pradesh"},{"Pincode":"481111","Name":"Piparia B.O","Block":"Baihar","District":"Balaghat","State":"Madhya Pradesh"},{"Pincode":"481331","Name":"Piparia Bhandi B.O","Block":"Waraseoni","District":"Balaghat","State":"Madhya Pradesh"},{"Pincode":"481105","Name":"Pondi B.O","Block":"Baihar","District":"Balaghat","State":"Madhya Pradesh"},{"Pincode":"481117","Name":"Pondi B.O","Block":"Baihar","District":"Balaghat","State":"Madhya Pradesh"},{"Pincode":"481449","Name":"Pouniya B.O","Block":"Katangi","District":"Balaghat","State":"Madhya Pradesh"},{"Pincode":"481449","Name":"Pulputta B.O","Block":"Katangi","District":"Balaghat","State":"Madhya Pradesh"},{"Pincode":"481115","Name":"Rajegaon B.O","Block":"Kirnapur","District":"Balaghat","State":"Madhya Pradesh"},{"Pincode":"481115","Name":"Ramgarhi B.O","Block":"Kirnapur","District":"Balaghat","State":"Madhya Pradesh"},{"Pincode":"481335","Name":"Rampaily S.O","Block":"Waraseoni","District":"Balaghat","State":"Madhya Pradesh"},{"Pincode":"481332","Name":"Ramrama B.O","Block":"Waraseoni","District":"Balaghat","State":"Madhya Pradesh"},{"Pincode":"481115","Name":"Rankakodi B.O","Block":"Kirnapur","District":"Balaghat","State":"Madhya Pradesh"},{"Pincode":"481051","Name":"Relwahi B.O","Block":"Baihar","District":"Balaghat","State":"Madhya Pradesh"},{"Pincode":"481222","Name":"Risewara B.O","Block":"Lanji","District":"Balaghat","State":"Madhya Pradesh"},{"Pincode":"481105","Name":"Roopjhar B.O","Block":"Baihar","District":"Balaghat","State":"Madhya Pradesh"},{"Pincode":"481001","Name":"Roshna B.O","Block":"Balaghat","District":"Balaghat","State":"Madhya Pradesh"},{"Pincode":"481224","Name":"Sadra B.O","Block":"Lanji","District":"Balaghat","State":"Madhya Pradesh"},{"Pincode":"481335","Name":"Salebardi B.O","Block":"Waraseoni","District":"Balaghat","State":"Madhya Pradesh"},{"Pincode":"481226","Name":"Saleteka B.O","Block":"Kirnapur","District":"Balaghat","State":"Madhya Pradesh"},{"Pincode":"481337","Name":"Saleteka B.O","Block":"Khairlanji","District":"Balaghat","State":"Madhya Pradesh"},{"Pincode":"481051","Name":"Saletekari B.O","Block":"Baihar","District":"Balaghat","State":"Madhya Pradesh"},{"Pincode":"481001","Name":"Samnapur B.O","Block":"Balaghat","District":"Balaghat","State":"Madhya Pradesh"},{"Pincode":"481337","Name":"Saori B.O","Block":"Khairlanji","District":"Balaghat","State":"Madhya Pradesh"},{"Pincode":"481111","Name":"Sarekha B.O","Block":"Baihar","District":"Balaghat","State":"Madhya Pradesh"},{"Pincode":"481001","Name":"Sarekha-kosmi S.O","Block":"Balaghat","District":"Balaghat","State":"Madhya Pradesh"},{"Pincode":"481332","Name":"Sawan R.S. B.O","Block":"Waraseoni","District":"Balaghat","State":"Madhya Pradesh"},{"Pincode":"481222","Name":"Sawari B.O","Block":"Lanji","District":"Balaghat","State":"Madhya Pradesh"},{"Pincode":"481445","Name":"Selwa B.O","Block":"Katangi","District":"Balaghat","State":"Madhya Pradesh"},{"Pincode":"481115","Name":"Sewati B.O","Block":"Kiranpur","District":"Balaghat","State":"Madhya Pradesh"},{"Pincode":"481337","Name":"Shankar Pipariya B.O","Block":"Khairlanji","District":"Balaghat","State":"Madhya Pradesh"},{"Pincode":"481441","Name":"Sihora B.O","Block":"Lalbarra","District":"Balaghat","State":"Madhya Pradesh"},{"Pincode":"481117","Name":"Sijhora B.O","Block":"Baihar","District":"Balaghat","State":"Madhya Pradesh"},{"Pincode":"481332","Name":"Sirpur B.O","Block":"Katangi","District":"Balaghat","State":"Madhya Pradesh"},{"Pincode":"481222","Name":"Sonarkakodi B.O","Block":"Lanji","District":"Balaghat","State":"Madhya Pradesh"},{"Pincode":"481105","Name":"Sonpur B.O","Block":"Baihar","District":"Balaghat","State":"Madhya Pradesh"},{"Pincode":"481449","Name":"Sukli B.O","Block":"Katangi","District":"Balaghat","State":"Madhya Pradesh"},{"Pincode":"481449","Name":"Tekadi B.O","Block":"Katangi","District":"Balaghat","State":"Madhya Pradesh"},{"Pincode":"481115","Name":"Temni B.O","Block":"Kirnapur","District":"Balaghat","State":"Madhya Pradesh"},{"Pincode":"481331","Name":"Thanegaon B.O","Block":"Waraseoni","District":"Balaghat","State":"Madhya Pradesh"},{"Pincode":"481556","Name":"Thema B.O","Block":"Baihar","District":"Balaghat","State":"Madhya Pradesh"},{"Pincode":"481051","Name":"Tingipur B.O","Block":"Baihar","District":"Balaghat","State":"Madhya Pradesh"},{"Pincode":"481449","Name":"Tirodi S.O","Block":"Katangi","District":"Balaghat","State":"Madhya Pradesh"},{"Pincode":"481445","Name":"Tumsar B.O","Block":"Katangi","District":"Balaghat","State":"Madhya Pradesh"},{"Pincode":"481105","Name":"Ukwa S.O","Block":"Balaghat","District":"Balaghat","State":"Madhya Pradesh"},{"Pincode":"481331","Name":"Waraseoni Civil Line S.O","Block":"Waraseoni","District":"Balaghat","State":"Madhya Pradesh"},{"Pincode":"481331","Name":"Waraseoni S.O","Block":"Waraseoni","District":"Balaghat","State":"Madhya Pradesh"}]